decouple-stubs/__init__.pyi
decouple_types-1.0.2.dist-info/LICENSE
decouple_types-1.0.2.dist-info/METADATA
decouple_types-1.0.2.dist-info/WHEEL
decouple_types-1.0.2.dist-info/RECORD
